responsum/__init__.py
responsum/_version.py
responsum/response.py
responsum/utils/__init__.py
responsum/utils/file_utils.py
responsum/utils/fits_file.py
responsum/utils/package_data.py
responsum-0.1.3.dist-info/LICENSE
responsum-0.1.3.dist-info/METADATA
responsum-0.1.3.dist-info/WHEEL
responsum-0.1.3.dist-info/top_level.txt
responsum-0.1.3.dist-info/RECORD
