Metadata-Version: 2.1
Name: responsum
Version: 0.1.3
Summary: A generic dispersion response library
Home-page: https://github.com/grburgess/responsum
Author: J. Michael Burgess
Author-email: jmichaelburgess@gmail.com
License: GPL3
Project-URL: Bug Tracker, https://github.com/grburgess/responsum/issues
Project-URL: Source Code, https://github.com/grburgess/responsum
Platform: UNKNOWN
Requires-Dist: numpy
Requires-Dist: matplotlib
Requires-Dist: astropy
Requires-Dist: scipy
Requires-Dist: h5py
